{"blocks":[{"x":410,"y":110,"text":"начало","width":100,"height":30,"type":"Начало / конец","isMenuBlock":false,"fontSize":14,"textHeight":14,"isBold":false,"isItalic":false,"textAlign":"center","labelsPosition":1},{"x":410,"y":170,"text":"int array[10];\r\n int array2[10]","width":100,"height":40,"type":"Блок","isMenuBlock":false,"fontSize":14,"textHeight":14,"isBold":false,"isItalic":false,"textAlign":"center","labelsPosition":1},{"x":410,"y":240,"text":"i от 0 до 10,i++","width":140,"height":40,"type":"Цикл for","isMenuBlock":false,"fontSize":14,"textHeight":14,"isBold":false,"isItalic":false,"textAlign":"center","labelsPosition":1},{"x":410,"y":300,"text":"array[i] = rand() % 100","width":180,"height":40,"type":"Блок","isMenuBlock":false,"fontSize":14,"textHeight":14,"isBold":false,"isItalic":false,"textAlign":"center","labelsPosition":1},{"x":410,"y":360,"text":"array[i] % 2 == 0","width":140,"height":40,"type":"Условие","isMenuBlock":false,"fontSize":14,"textHeight":14,"isBold":false,"isItalic":false,"textAlign":"center","labelsPosition":1},{"x":300,"y":400,"text":"array2[i] = 1","width":100,"height":40,"type":"Блок","isMenuBlock":false,"fontSize":14,"textHeight":14,"isBold":false,"isItalic":false,"textAlign":"center","labelsPosition":1},{"x":530,"y":400,"text":"array2[i] = array[i]","width":100,"height":40,"type":"Блок","isMenuBlock":false,"fontSize":14,"textHeight":14,"isBold":false,"isItalic":false,"textAlign":"center","labelsPosition":1},{"x":410,"y":490,"text":"i от 0 до 10,i++","width":100,"height":40,"type":"Цикл for","isMenuBlock":false,"fontSize":14,"textHeight":14,"isBold":false,"isItalic":false,"textAlign":"center","labelsPosition":1},{"x":410,"y":550,"text":"array2[i]!=1","width":100,"height":40,"type":"Условие","isMenuBlock":false,"fontSize":14,"textHeight":14,"isBold":false,"isItalic":false,"textAlign":"center","labelsPosition":1},{"x":500,"y":600,"text":" array2[i]","width":120,"height":40,"type":"Ввод / вывод","isMenuBlock":false,"fontSize":14,"textHeight":14,"isBold":false,"isItalic":false,"textAlign":"center","labelsPosition":1},{"x":410,"y":690,"text":"end","width":100,"height":30,"type":"Начало / конец","isMenuBlock":false,"fontSize":14,"textHeight":14,"isBold":false,"isItalic":false,"textAlign":"center","labelsPosition":1},{"x":400,"y":800,"text":"начало","width":100,"height":30,"type":"Начало / конец","isMenuBlock":false,"fontSize":14,"textHeight":14,"isBold":false,"isItalic":false,"textAlign":"center","labelsPosition":1},{"x":400,"y":920,"text":"prov=true","width":100,"height":40,"type":"Блок","isMenuBlock":false,"fontSize":14,"textHeight":14,"isBold":false,"isItalic":false,"textAlign":"center","labelsPosition":1},{"x":400,"y":980,"text":"j от 0 до count","width":100,"height":40,"type":"Цикл for","isMenuBlock":false,"fontSize":14,"textHeight":14,"isBold":false,"isItalic":false,"textAlign":"center","labelsPosition":1},{"x":400,"y":1040,"text":"strcmp(array[i],array2[j]) == 0","width":260,"height":40,"type":"Условие","isMenuBlock":false,"fontSize":14,"textHeight":14,"isBold":false,"isItalic":false,"textAlign":"center","labelsPosition":1},{"x":570,"y":1090,"text":" prov = false","width":100,"height":40,"type":"Блок","isMenuBlock":false,"fontSize":14,"textHeight":14,"isBold":false,"isItalic":false,"textAlign":"center","labelsPosition":1},{"x":570,"y":1150,"text":"break","width":100,"height":40,"type":"Блок","isMenuBlock":false,"fontSize":14,"textHeight":14,"isBold":false,"isItalic":false,"textAlign":"center","labelsPosition":1},{"x":400,"y":1250,"text":"prov==true","width":100,"height":40,"type":"Условие","isMenuBlock":false,"fontSize":14,"textHeight":14,"isBold":false,"isItalic":false,"textAlign":"center","labelsPosition":1},{"x":490,"y":1300,"text":"strcpy(array2[count], array[i])","width":200,"height":40,"type":"Блок","isMenuBlock":false,"fontSize":14,"textHeight":14,"isBold":false,"isItalic":false,"textAlign":"center","labelsPosition":1},{"x":490,"y":1360,"text":"count++","width":100,"height":40,"type":"Блок","isMenuBlock":false,"fontSize":14,"textHeight":14,"isBold":false,"isItalic":false,"textAlign":"center","labelsPosition":1},{"x":400,"y":1460,"text":"i от 0 до 3","width":100,"height":40,"type":"Цикл for","isMenuBlock":false,"fontSize":14,"textHeight":14,"isBold":false,"isItalic":false,"textAlign":"center","labelsPosition":1},{"x":400,"y":860,"text":"i от 1 до 3,i++","width":100,"height":40,"type":"Цикл for","isMenuBlock":false,"fontSize":14,"textHeight":14,"isBold":false,"isItalic":false,"textAlign":"center","labelsPosition":1},{"x":400,"y":1530,"text":"array2[i]","width":120,"height":40,"type":"Ввод / вывод","isMenuBlock":false,"fontSize":14,"textHeight":14,"isBold":false,"isItalic":false,"textAlign":"center","labelsPosition":1},{"x":400,"y":1620,"text":"end","width":100,"height":30,"type":"Начало / конец","isMenuBlock":false,"fontSize":14,"textHeight":14,"isBold":false,"isItalic":false,"textAlign":"center","labelsPosition":1},{"x":400,"y":1720,"text":"начало","width":100,"height":30,"type":"Начало / конец","isMenuBlock":false,"fontSize":14,"textHeight":14,"isBold":false,"isItalic":false,"textAlign":"center","labelsPosition":1},{"x":400,"y":1780,"text":"WeatherData today","width":140,"height":40,"type":"Блок","isMenuBlock":false,"fontSize":14,"textHeight":14,"isBold":false,"isItalic":false,"textAlign":"center","labelsPosition":1},{"x":400,"y":1840,"text":"today = { 20.3,43.13,150.2 }","width":180,"height":40,"type":"Блок","isMenuBlock":false,"fontSize":14,"textHeight":14,"isBold":false,"isItalic":false,"textAlign":"center","labelsPosition":1},{"x":400,"y":1910,"text":"today.temperature\ntoday.humidity\ntoday.windSpeed","width":120,"height":60,"type":"Ввод / вывод","isMenuBlock":false,"fontSize":14,"textHeight":14,"isBold":false,"isItalic":false,"textAlign":"center","labelsPosition":1},{"x":400,"y":1980,"text":"end","width":100,"height":30,"type":"Начало / конец","isMenuBlock":false,"fontSize":14,"textHeight":14,"isBold":false,"isItalic":false,"textAlign":"center","labelsPosition":1},{"x":405,"y":1680,"text":"main","width":50,"height":20,"type":"Текст / комментарий","isMenuBlock":false,"fontSize":14,"textHeight":14,"isBold":false,"isItalic":false,"textAlign":"left","labelsPosition":1},{"x":645,"y":1680,"text":"weatherData","width":90,"height":20,"type":"Текст / комментарий","isMenuBlock":false,"fontSize":14,"textHeight":14,"isBold":false,"isItalic":false,"textAlign":"left","labelsPosition":1},{"x":650,"y":1720,"text":"начало","width":100,"height":30,"type":"Начало / конец","isMenuBlock":false,"fontSize":14,"textHeight":14,"isBold":false,"isItalic":false,"textAlign":"center","labelsPosition":1},{"x":650,"y":1790,"text":"temperature\nhumidity\nwindSpeed","width":100,"height":60,"type":"Блок","isMenuBlock":false,"fontSize":14,"textHeight":14,"isBold":false,"isItalic":false,"textAlign":"center","labelsPosition":1},{"x":650,"y":1850,"text":"end","width":100,"height":30,"type":"Начало / конец","isMenuBlock":false,"fontSize":14,"textHeight":14,"isBold":false,"isItalic":false,"textAlign":"center","labelsPosition":1},{"x":400,"y":2090,"text":"начало","width":100,"height":30,"type":"Начало / конец","isMenuBlock":false,"fontSize":14,"textHeight":14,"isBold":false,"isItalic":false,"textAlign":"center","labelsPosition":1},{"x":400,"y":2150,"text":"Graph g","width":100,"height":40,"type":"Блок","isMenuBlock":false,"fontSize":14,"textHeight":14,"isBold":false,"isItalic":false,"textAlign":"center","labelsPosition":1},{"x":400,"y":2210,"text":"g.dob()","width":100,"height":40,"type":"Блок","isMenuBlock":false,"fontSize":14,"textHeight":14,"isBold":false,"isItalic":false,"textAlign":"center","labelsPosition":1},{"x":400,"y":2270,"text":"g.del()","width":100,"height":40,"type":"Блок","isMenuBlock":false,"fontSize":14,"textHeight":14,"isBold":false,"isItalic":false,"textAlign":"center","labelsPosition":1},{"x":400,"y":2330,"text":"g.add()","width":100,"height":40,"type":"Блок","isMenuBlock":false,"fontSize":14,"textHeight":14,"isBold":false,"isItalic":false,"textAlign":"center","labelsPosition":1},{"x":400,"y":2390,"text":"g.print()","width":100,"height":40,"type":"Блок","isMenuBlock":false,"fontSize":14,"textHeight":14,"isBold":false,"isItalic":false,"textAlign":"center","labelsPosition":1},{"x":400,"y":2450,"text":"g.add()","width":100,"height":40,"type":"Блок","isMenuBlock":false,"fontSize":14,"textHeight":14,"isBold":false,"isItalic":false,"textAlign":"center","labelsPosition":1},{"x":400,"y":2510,"text":"g.print()","width":100,"height":40,"type":"Блок","isMenuBlock":false,"fontSize":14,"textHeight":14,"isBold":false,"isItalic":false,"textAlign":"center","labelsPosition":1},{"x":400,"y":2570,"text":"g.delreb()","width":100,"height":40,"type":"Блок","isMenuBlock":false,"fontSize":14,"textHeight":14,"isBold":false,"isItalic":false,"textAlign":"center","labelsPosition":1},{"x":400,"y":2630,"text":"g.print()","width":100,"height":40,"type":"Блок","isMenuBlock":false,"fontSize":14,"textHeight":14,"isBold":false,"isItalic":false,"textAlign":"center","labelsPosition":1},{"x":400,"y":2690,"text":"end","width":100,"height":30,"type":"Начало / конец","isMenuBlock":false,"fontSize":14,"textHeight":14,"isBold":false,"isItalic":false,"textAlign":"center","labelsPosition":1},{"x":405,"y":2060,"text":"main","width":50,"height":20,"type":"Текст / комментарий","isMenuBlock":false,"fontSize":14,"textHeight":14,"isBold":false,"isItalic":false,"textAlign":"left","labelsPosition":1},{"x":725,"y":2090,"text":"Конструктор","width":90,"height":20,"type":"Текст / комментарий","isMenuBlock":false,"fontSize":14,"textHeight":14,"isBold":false,"isItalic":false,"textAlign":"left","labelsPosition":1},{"x":720,"y":2130,"text":"начало","width":100,"height":30,"type":"Начало / конец","isMenuBlock":false,"fontSize":14,"textHeight":14,"isBold":false,"isItalic":false,"textAlign":"center","labelsPosition":1},{"x":720,"y":2190,"text":"a","width":120,"height":40,"type":"Ввод / вывод","isMenuBlock":false,"fontSize":14,"textHeight":14,"isBold":false,"isItalic":false,"textAlign":"center","labelsPosition":1},{"x":720,"y":2250,"text":"a>=10","width":100,"height":40,"type":"Условие","isMenuBlock":false,"fontSize":14,"textHeight":14,"isBold":false,"isItalic":false,"textAlign":"center","labelsPosition":1},{"x":850,"y":2280,"text":"a=5","width":100,"height":40,"type":"Блок","isMenuBlock":false,"fontSize":14,"textHeight":14,"isBold":false,"isItalic":false,"textAlign":"center","labelsPosition":1},{"x":720,"y":2350,"text":"i от 0 до a,i++","width":100,"height":40,"type":"Цикл for","isMenuBlock":false,"fontSize":14,"textHeight":14,"isBold":false,"isItalic":false,"textAlign":"center","labelsPosition":1},{"x":720,"y":2410,"text":"countver++","width":100,"height":40,"type":"Блок","isMenuBlock":false,"fontSize":14,"textHeight":14,"isBold":false,"isItalic":false,"textAlign":"center","labelsPosition":1},{"x":720,"y":2470,"text":"ver[i]=countver","width":100,"height":40,"type":"Блок","isMenuBlock":false,"fontSize":14,"textHeight":14,"isBold":false,"isItalic":false,"textAlign":"center","labelsPosition":1},{"x":720,"y":2530,"text":"ver[i]","width":120,"height":40,"type":"Ввод / вывод","isMenuBlock":false,"fontSize":14,"textHeight":14,"isBold":false,"isItalic":false,"textAlign":"center","labelsPosition":1},{"x":720,"y":2580,"text":"end","width":100,"height":30,"type":"Начало / конец","isMenuBlock":false,"fontSize":14,"textHeight":14,"isBold":false,"isItalic":false,"textAlign":"center","labelsPosition":1},{"x":1000,"y":2080,"text":"add","width":40,"height":20,"type":"Текст / комментарий","isMenuBlock":false,"fontSize":14,"textHeight":14,"isBold":false,"isItalic":false,"textAlign":"left","labelsPosition":1},{"x":1030,"y":2120,"text":"начало","width":100,"height":30,"type":"Начало / конец","isMenuBlock":false,"fontSize":14,"textHeight":14,"isBold":false,"isItalic":false,"textAlign":"center","labelsPosition":1},{"x":1030,"y":2180,"text":"st,ed","width":120,"height":40,"type":"Ввод / вывод","isMenuBlock":false,"fontSize":14,"textHeight":14,"isBold":false,"isItalic":false,"textAlign":"center","labelsPosition":1},{"x":1030,"y":2240,"text":"pr1 = false;\r\npr2 = false","width":100,"height":40,"type":"Блок","isMenuBlock":false,"fontSize":14,"textHeight":14,"isBold":false,"isItalic":false,"textAlign":"center","labelsPosition":1},{"x":1030,"y":2300,"text":"i от 0 до countver","width":140,"height":40,"type":"Цикл for","isMenuBlock":false,"fontSize":14,"textHeight":14,"isBold":false,"isItalic":false,"textAlign":"center","labelsPosition":1},{"x":1030,"y":2360,"text":"ver[i] == st","width":100,"height":40,"type":"Условие","isMenuBlock":false,"fontSize":14,"textHeight":14,"isBold":false,"isItalic":false,"textAlign":"center","labelsPosition":1},{"x":1030,"y":2430,"text":"ver[i] == ed","width":100,"height":40,"type":"Условие","isMenuBlock":false,"fontSize":14,"textHeight":14,"isBold":false,"isItalic":false,"textAlign":"center","labelsPosition":1},{"x":1170,"y":2360,"text":"pr1 = true","width":100,"height":40,"type":"Блок","isMenuBlock":false,"fontSize":14,"textHeight":14,"isBold":false,"isItalic":false,"textAlign":"center","labelsPosition":1},{"x":1170,"y":2430,"text":"pr2 = true","width":100,"height":40,"type":"Блок","isMenuBlock":false,"fontSize":14,"textHeight":14,"isBold":false,"isItalic":false,"textAlign":"center","labelsPosition":1},{"x":1030,"y":2550,"text":"pr1 && pr2","width":100,"height":40,"type":"Условие","isMenuBlock":false,"fontSize":14,"textHeight":14,"isBold":false,"isItalic":false,"textAlign":"center","labelsPosition":1},{"x":1160,"y":2570,"text":"rbst[ec]=st","width":100,"height":40,"type":"Блок","isMenuBlock":false,"fontSize":14,"textHeight":14,"isBold":false,"isItalic":false,"textAlign":"center","labelsPosition":1},{"x":1160,"y":2690,"text":"ec++","width":100,"height":40,"type":"Блок","isMenuBlock":false,"fontSize":14,"textHeight":14,"isBold":false,"isItalic":false,"textAlign":"center","labelsPosition":1},{"x":1030,"y":2760,"text":"end","width":100,"height":30,"type":"Начало / конец","isMenuBlock":false,"fontSize":14,"textHeight":14,"isBold":false,"isItalic":false,"textAlign":"center","labelsPosition":1},{"x":1160,"y":2630,"text":"rbed[ec]=ed","width":100,"height":40,"type":"Блок","isMenuBlock":false,"fontSize":14,"textHeight":14,"isBold":false,"isItalic":false,"textAlign":"center","labelsPosition":1},{"x":1455,"y":2090,"text":"delreb","width":50,"height":20,"type":"Текст / комментарий","isMenuBlock":false,"fontSize":14,"textHeight":14,"isBold":false,"isItalic":false,"textAlign":"left","labelsPosition":1},{"x":1460,"y":2130,"text":"начало","width":100,"height":30,"type":"Начало / конец","isMenuBlock":false,"fontSize":14,"textHeight":14,"isBold":false,"isItalic":false,"textAlign":"center","labelsPosition":1},{"x":1460,"y":2190,"text":"st,ed","width":120,"height":40,"type":"Ввод / вывод","isMenuBlock":false,"fontSize":14,"textHeight":14,"isBold":false,"isItalic":false,"textAlign":"center","labelsPosition":1},{"x":1460,"y":2250,"text":"i от 0 до ec","width":100,"height":40,"type":"Цикл for","isMenuBlock":false,"fontSize":14,"textHeight":14,"isBold":false,"isItalic":false,"textAlign":"center","labelsPosition":1},{"x":1460,"y":2310,"text":"rbst[i] == st && rbed[i] == ed","width":220,"height":40,"type":"Условие","isMenuBlock":false,"fontSize":14,"textHeight":14,"isBold":false,"isItalic":false,"textAlign":"center","labelsPosition":1},{"x":1610,"y":2360,"text":"rbst[i]=rbst[ec-1]","width":100,"height":40,"type":"Блок","isMenuBlock":false,"fontSize":14,"textHeight":14,"isBold":false,"isItalic":false,"textAlign":"center","labelsPosition":1},{"x":1610,"y":2420,"text":"rbed[i]=rbed[ec-1]","width":120,"height":40,"type":"Блок","isMenuBlock":false,"fontSize":14,"textHeight":14,"isBold":false,"isItalic":false,"textAlign":"center","labelsPosition":1},{"x":1610,"y":2480,"text":"ec--","width":100,"height":40,"type":"Блок","isMenuBlock":false,"fontSize":14,"textHeight":14,"isBold":false,"isItalic":false,"textAlign":"center","labelsPosition":1},{"x":1610,"y":2540,"text":"break","width":100,"height":40,"type":"Блок","isMenuBlock":false,"fontSize":14,"textHeight":14,"isBold":false,"isItalic":false,"textAlign":"center","labelsPosition":1},{"x":1460,"y":2670,"text":"end","width":100,"height":30,"type":"Начало / конец","isMenuBlock":false,"fontSize":14,"textHeight":14,"isBold":false,"isItalic":false,"textAlign":"center","labelsPosition":1},{"x":1900,"y":2090,"text":"print","width":40,"height":20,"type":"Текст / комментарий","isMenuBlock":false,"fontSize":14,"textHeight":14,"isBold":false,"isItalic":false,"textAlign":"left","labelsPosition":1},{"x":1900,"y":2160,"text":"начало","width":100,"height":30,"type":"Начало / конец","isMenuBlock":false,"fontSize":14,"textHeight":14,"isBold":false,"isItalic":false,"textAlign":"center","labelsPosition":1},{"x":1900,"y":2220,"text":"i от 0 до countver","width":100,"height":40,"type":"Цикл for","isMenuBlock":false,"fontSize":14,"textHeight":14,"isBold":false,"isItalic":false,"textAlign":"center","labelsPosition":1},{"x":1900,"y":2280,"text":"ver[i]","width":120,"height":40,"type":"Ввод / вывод","isMenuBlock":false,"fontSize":14,"textHeight":14,"isBold":false,"isItalic":false,"textAlign":"center","labelsPosition":1},{"x":1900,"y":2360,"text":"i от 0 до ec","width":100,"height":40,"type":"Цикл for","isMenuBlock":false,"fontSize":14,"textHeight":14,"isBold":false,"isItalic":false,"textAlign":"center","labelsPosition":1},{"x":1900,"y":2420,"text":"rbst[i],rbed[i]","width":160,"height":40,"type":"Ввод / вывод","isMenuBlock":false,"fontSize":14,"textHeight":14,"isBold":false,"isItalic":false,"textAlign":"center","labelsPosition":1},{"x":1900,"y":2490,"text":"end","width":100,"height":30,"type":"Начало / конец","isMenuBlock":false,"fontSize":14,"textHeight":14,"isBold":false,"isItalic":false,"textAlign":"center","labelsPosition":1},{"x":2140,"y":2090,"text":"dob","width":40,"height":20,"type":"Текст / комментарий","isMenuBlock":false,"fontSize":14,"textHeight":14,"isBold":false,"isItalic":false,"textAlign":"left","labelsPosition":1},{"x":2140,"y":2150,"text":"начало","width":100,"height":30,"type":"Начало / конец","isMenuBlock":false,"fontSize":14,"textHeight":14,"isBold":false,"isItalic":false,"textAlign":"center","labelsPosition":1},{"x":2140,"y":2210,"text":"countver<10","width":100,"height":40,"type":"Условие","isMenuBlock":false,"fontSize":14,"textHeight":14,"isBold":false,"isItalic":false,"textAlign":"center","labelsPosition":1},{"x":2250,"y":2260,"text":"  ver[countver] = countver+ 1","width":100,"height":40,"type":"Блок","isMenuBlock":false,"fontSize":14,"textHeight":14,"isBold":false,"isItalic":false,"textAlign":"center","labelsPosition":1},{"x":2250,"y":2320,"text":"countver++","width":100,"height":40,"type":"Блок","isMenuBlock":false,"fontSize":14,"textHeight":14,"isBold":false,"isItalic":false,"textAlign":"center","labelsPosition":1},{"x":2140,"y":2390,"text":"end","width":100,"height":30,"type":"Начало / конец","isMenuBlock":false,"fontSize":14,"textHeight":14,"isBold":false,"isItalic":false,"textAlign":"center","labelsPosition":1},{"x":2440,"y":2090,"text":"del","width":40,"height":20,"type":"Текст / комментарий","isMenuBlock":false,"fontSize":14,"textHeight":14,"isBold":false,"isItalic":false,"textAlign":"left","labelsPosition":1},{"x":2440,"y":2150,"text":"начало","width":100,"height":30,"type":"Начало / конец","isMenuBlock":false,"fontSize":14,"textHeight":14,"isBold":false,"isItalic":false,"textAlign":"center","labelsPosition":1},{"x":2440,"y":2210,"text":"countver--","width":100,"height":40,"type":"Блок","isMenuBlock":false,"fontSize":14,"textHeight":14,"isBold":false,"isItalic":false,"textAlign":"center","labelsPosition":1},{"x":2440,"y":2270,"text":" ver[countver] = NULL","width":100,"height":40,"type":"Блок","isMenuBlock":false,"fontSize":14,"textHeight":14,"isBold":false,"isItalic":false,"textAlign":"center","labelsPosition":1},{"x":2440,"y":2320,"text":"end","width":100,"height":30,"type":"Начало / конец","isMenuBlock":false,"fontSize":14,"textHeight":14,"isBold":false,"isItalic":false,"textAlign":"center","labelsPosition":1},{"x":1605,"y":1990,"text":"Graph","width":50,"height":20,"type":"Текст / комментарий","isMenuBlock":false,"fontSize":14,"textHeight":14,"isBold":false,"isItalic":false,"textAlign":"left","labelsPosition":1}],"arrows":[{"startIndex":0,"endIndex":1,"startConnectorIndex":2,"endConnectorIndex":0,"nodes":[{"x":410,"y":125},{"x":410,"y":130},{"x":410,"y":150}],"counts":[1,1,1]},{"startIndex":2,"endIndex":3,"startConnectorIndex":2,"endConnectorIndex":0,"nodes":[{"x":410,"y":260},{"x":410,"y":260},{"x":410,"y":280}],"counts":[1,1,1]},{"startIndex":1,"endIndex":2,"startConnectorIndex":2,"endConnectorIndex":0,"nodes":[{"x":410,"y":190},{"x":410,"y":200},{"x":410,"y":220}],"counts":[1,1,1]},{"startIndex":3,"endIndex":4,"startConnectorIndex":2,"endConnectorIndex":0,"nodes":[{"x":410,"y":320},{"x":410,"y":320},{"x":410,"y":340}],"counts":[1,1,1]},{"startIndex":4,"endIndex":5,"startConnectorIndex":3,"endConnectorIndex":0,"nodes":[{"x":340,"y":360},{"x":300,"y":360},{"x":300,"y":380}],"counts":[1,1,1]},{"startIndex":4,"endIndex":6,"startConnectorIndex":1,"endConnectorIndex":0,"nodes":[{"x":480,"y":360},{"x":530,"y":360},{"x":530,"y":380}],"counts":[1,1,1]},{"startIndex":6,"endIndex":2,"startConnectorIndex":2,"endConnectorIndex":1,"nodes":[{"x":530,"y":420},{"x":530,"y":440},{"x":640,"y":440},{"x":640,"y":240},{"x":500,"y":240},{"x":480,"y":240}],"counts":[1,1,1,1,1,1]},{"startIndex":5,"endIndex":2,"startConnectorIndex":2,"endConnectorIndex":1,"nodes":[{"x":300,"y":420},{"x":300,"y":440},{"x":640,"y":440},{"x":640,"y":240},{"x":480,"y":240}],"counts":[1,1,1,1,1]},{"startIndex":7,"endIndex":8,"startConnectorIndex":2,"endConnectorIndex":0,"nodes":[{"x":410,"y":510},{"x":410,"y":510},{"x":410,"y":530}],"counts":[1,1,1]},{"startIndex":8,"endIndex":9,"startConnectorIndex":1,"endConnectorIndex":0,"nodes":[{"x":460,"y":550},{"x":500,"y":550},{"x":500,"y":560},{"x":500,"y":580}],"counts":[1,1,1,1]},{"startIndex":9,"endIndex":7,"startConnectorIndex":1,"endConnectorIndex":1,"nodes":[{"x":560,"y":600},{"x":590,"y":600},{"x":590,"y":490},{"x":480,"y":490},{"x":460,"y":490}],"counts":[1,1,1,1,1]},{"startIndex":8,"endIndex":7,"startConnectorIndex":3,"endConnectorIndex":1,"nodes":[{"x":360,"y":550},{"x":340,"y":550},{"x":340,"y":650},{"x":590,"y":650},{"x":590,"y":490},{"x":480,"y":490},{"x":460,"y":490}],"counts":[1,1,1,1,1,1,1]},{"startIndex":2,"endIndex":7,"startConnectorIndex":3,"endConnectorIndex":0,"nodes":[{"x":340,"y":240},{"x":240,"y":240},{"x":240,"y":450},{"x":410,"y":450},{"x":410,"y":470}],"counts":[1,1,1,1,1]},{"startIndex":7,"endIndex":10,"startConnectorIndex":3,"endConnectorIndex":3,"nodes":[{"x":360,"y":490},{"x":300,"y":490},{"x":300,"y":690},{"x":340,"y":690},{"x":360,"y":690}],"counts":[1,1,1,1,1]},{"startIndex":11,"endIndex":21,"startConnectorIndex":2,"endConnectorIndex":0,"nodes":[{"x":400,"y":815},{"x":400,"y":820},{"x":400,"y":840}],"counts":[1,1,1]},{"startIndex":21,"endIndex":12,"startConnectorIndex":2,"endConnectorIndex":0,"nodes":[{"x":400,"y":880},{"x":400,"y":880},{"x":400,"y":900}],"counts":[1,1,1]},{"startIndex":12,"endIndex":13,"startConnectorIndex":2,"endConnectorIndex":0,"nodes":[{"x":400,"y":940},{"x":400,"y":940},{"x":400,"y":960}],"counts":[1,1,1]},{"startIndex":13,"endIndex":14,"startConnectorIndex":2,"endConnectorIndex":0,"nodes":[{"x":400,"y":1000},{"x":400,"y":1000},{"x":400,"y":1020}],"counts":[1,1,1]},{"startIndex":15,"endIndex":16,"startConnectorIndex":2,"endConnectorIndex":0,"nodes":[{"x":570,"y":1110},{"x":570,"y":1110},{"x":570,"y":1130}],"counts":[1,1,1]},{"startIndex":14,"endIndex":15,"startConnectorIndex":1,"endConnectorIndex":0,"nodes":[{"x":530,"y":1040},{"x":570,"y":1040},{"x":570,"y":1050},{"x":570,"y":1070}],"counts":[1,1,1,1]},{"startIndex":18,"endIndex":19,"startConnectorIndex":2,"endConnectorIndex":0,"nodes":[{"x":490,"y":1320},{"x":490,"y":1320},{"x":490,"y":1340}],"counts":[1,1,1]},{"startIndex":17,"endIndex":18,"startConnectorIndex":1,"endConnectorIndex":0,"nodes":[{"x":450,"y":1250},{"x":490,"y":1250},{"x":490,"y":1260},{"x":490,"y":1280}],"counts":[1,1,1,1]},{"startIndex":13,"endIndex":17,"startConnectorIndex":3,"endConnectorIndex":0,"nodes":[{"x":350,"y":980},{"x":230,"y":980},{"x":230,"y":1210},{"x":400,"y":1210},{"x":400,"y":1230}],"counts":[1,1,1,1,1]},{"startIndex":19,"endIndex":21,"startConnectorIndex":2,"endConnectorIndex":1,"nodes":[{"x":490,"y":1380},{"x":490,"y":1400},{"x":700,"y":1400},{"x":700,"y":860},{"x":470,"y":860},{"x":450,"y":860}],"counts":[1,1,1,1,1,1]},{"startIndex":17,"endIndex":21,"startConnectorIndex":3,"endConnectorIndex":1,"nodes":[{"x":350,"y":1250},{"x":330,"y":1250},{"x":330,"y":1400},{"x":700,"y":1400},{"x":700,"y":860},{"x":450,"y":860}],"counts":[1,1,1,1,1,1]},{"startIndex":21,"endIndex":20,"startConnectorIndex":3,"endConnectorIndex":0,"nodes":[{"x":350,"y":860},{"x":210,"y":860},{"x":210,"y":1420},{"x":400,"y":1420},{"x":400,"y":1440}],"counts":[1,1,1,1,1]},{"startIndex":20,"endIndex":22,"startConnectorIndex":2,"endConnectorIndex":0,"nodes":[{"x":400,"y":1480},{"x":400,"y":1490},{"x":400,"y":1510}],"counts":[1,1,1]},{"startIndex":22,"endIndex":20,"startConnectorIndex":1,"endConnectorIndex":1,"nodes":[{"x":460,"y":1530},{"x":490,"y":1530},{"x":490,"y":1460},{"x":470,"y":1460},{"x":450,"y":1460}],"counts":[1,1,1,1,1]},{"startIndex":20,"endIndex":23,"startConnectorIndex":3,"endConnectorIndex":0,"nodes":[{"x":350,"y":1460},{"x":330,"y":1460},{"x":330,"y":1590},{"x":400,"y":1590},{"x":400,"y":1605}],"counts":[1,1,1,1,1]},{"startIndex":24,"endIndex":25,"startConnectorIndex":2,"endConnectorIndex":0,"nodes":[{"x":400,"y":1735},{"x":400,"y":1740},{"x":400,"y":1760}],"counts":[1,1,1]},{"startIndex":25,"endIndex":26,"startConnectorIndex":2,"endConnectorIndex":0,"nodes":[{"x":400,"y":1800},{"x":400,"y":1800},{"x":400,"y":1820}],"counts":[1,1,1]},{"startIndex":26,"endIndex":27,"startConnectorIndex":2,"endConnectorIndex":0,"nodes":[{"x":400,"y":1860},{"x":400,"y":1860},{"x":400,"y":1880}],"counts":[1,1,1]},{"startIndex":27,"endIndex":28,"startConnectorIndex":2,"endConnectorIndex":0,"nodes":[{"x":400,"y":1940},{"x":400,"y":1950},{"x":400,"y":1965}],"counts":[1,1,1]},{"startIndex":31,"endIndex":32,"startConnectorIndex":2,"endConnectorIndex":0,"nodes":[{"x":650,"y":1735},{"x":650,"y":1740},{"x":650,"y":1760}],"counts":[1,1,1]},{"startIndex":32,"endIndex":33,"startConnectorIndex":2,"endConnectorIndex":0,"nodes":[{"x":650,"y":1820},{"x":650,"y":1820},{"x":650,"y":1835}],"counts":[1,1,1]},{"startIndex":34,"endIndex":35,"startConnectorIndex":2,"endConnectorIndex":0,"nodes":[{"x":400,"y":2105},{"x":400,"y":2110},{"x":400,"y":2130}],"counts":[1,1,1]},{"startIndex":35,"endIndex":36,"startConnectorIndex":2,"endConnectorIndex":0,"nodes":[{"x":400,"y":2170},{"x":400,"y":2170},{"x":400,"y":2190}],"counts":[1,1,1]},{"startIndex":36,"endIndex":37,"startConnectorIndex":2,"endConnectorIndex":0,"nodes":[{"x":400,"y":2230},{"x":400,"y":2230},{"x":400,"y":2250}],"counts":[1,1,1]},{"startIndex":37,"endIndex":38,"startConnectorIndex":2,"endConnectorIndex":0,"nodes":[{"x":400,"y":2290},{"x":400,"y":2290},{"x":400,"y":2310}],"counts":[1,1,1]},{"startIndex":38,"endIndex":39,"startConnectorIndex":2,"endConnectorIndex":0,"nodes":[{"x":400,"y":2350},{"x":400,"y":2350},{"x":400,"y":2370}],"counts":[1,1,1]},{"startIndex":39,"endIndex":40,"startConnectorIndex":2,"endConnectorIndex":0,"nodes":[{"x":400,"y":2410},{"x":400,"y":2410},{"x":400,"y":2430}],"counts":[1,1,1]},{"startIndex":40,"endIndex":41,"startConnectorIndex":2,"endConnectorIndex":0,"nodes":[{"x":400,"y":2470},{"x":400,"y":2470},{"x":400,"y":2490}],"counts":[1,1,1]},{"startIndex":41,"endIndex":42,"startConnectorIndex":2,"endConnectorIndex":0,"nodes":[{"x":400,"y":2530},{"x":400,"y":2530},{"x":400,"y":2550}],"counts":[1,1,1]},{"startIndex":42,"endIndex":43,"startConnectorIndex":2,"endConnectorIndex":0,"nodes":[{"x":400,"y":2590},{"x":400,"y":2590},{"x":400,"y":2610}],"counts":[1,1,1]},{"startIndex":43,"endIndex":44,"startConnectorIndex":2,"endConnectorIndex":0,"nodes":[{"x":400,"y":2650},{"x":400,"y":2660},{"x":400,"y":2675}],"counts":[1,1,1]},{"startIndex":47,"endIndex":48,"startConnectorIndex":2,"endConnectorIndex":0,"nodes":[{"x":720,"y":2145},{"x":720,"y":2150},{"x":720,"y":2170}],"counts":[1,1,1]},{"startIndex":48,"endIndex":49,"startConnectorIndex":2,"endConnectorIndex":0,"nodes":[{"x":720,"y":2210},{"x":720,"y":2210},{"x":720,"y":2230}],"counts":[1,1,1]},{"startIndex":49,"endIndex":50,"startConnectorIndex":1,"endConnectorIndex":0,"nodes":[{"x":770,"y":2250},{"x":850,"y":2250},{"x":850,"y":2260}],"counts":[1,1,1]},{"startIndex":50,"endIndex":51,"startConnectorIndex":2,"endConnectorIndex":0,"nodes":[{"x":850,"y":2300},{"x":850,"y":2310},{"x":720,"y":2310},{"x":720,"y":2330}],"counts":[1,1,1,1]},{"startIndex":49,"endIndex":51,"startConnectorIndex":3,"endConnectorIndex":0,"nodes":[{"x":670,"y":2250},{"x":650,"y":2250},{"x":650,"y":2310},{"x":720,"y":2310},{"x":720,"y":2330}],"counts":[1,1,1,1,1]},{"startIndex":51,"endIndex":52,"startConnectorIndex":2,"endConnectorIndex":0,"nodes":[{"x":720,"y":2370},{"x":720,"y":2370},{"x":720,"y":2390}],"counts":[1,1,1]},{"startIndex":52,"endIndex":53,"startConnectorIndex":2,"endConnectorIndex":0,"nodes":[{"x":720,"y":2430},{"x":720,"y":2430},{"x":720,"y":2450}],"counts":[1,1,1]},{"startIndex":53,"endIndex":54,"startConnectorIndex":2,"endConnectorIndex":0,"nodes":[{"x":720,"y":2490},{"x":720,"y":2490},{"x":720,"y":2510}],"counts":[1,1,1]},{"startIndex":54,"endIndex":55,"startConnectorIndex":2,"endConnectorIndex":0,"nodes":[{"x":720,"y":2550},{"x":720,"y":2550},{"x":720,"y":2565}],"counts":[1,1,1]},{"startIndex":57,"endIndex":58,"startConnectorIndex":2,"endConnectorIndex":0,"nodes":[{"x":1030,"y":2135},{"x":1030,"y":2140},{"x":1030,"y":2160}],"counts":[1,1,1]},{"startIndex":58,"endIndex":59,"startConnectorIndex":2,"endConnectorIndex":0,"nodes":[{"x":1030,"y":2200},{"x":1030,"y":2200},{"x":1030,"y":2220}],"counts":[1,1,1]},{"startIndex":59,"endIndex":60,"startConnectorIndex":2,"endConnectorIndex":0,"nodes":[{"x":1030,"y":2260},{"x":1030,"y":2260},{"x":1030,"y":2280}],"counts":[1,1,1]},{"startIndex":60,"endIndex":61,"startConnectorIndex":2,"endConnectorIndex":0,"nodes":[{"x":1030,"y":2320},{"x":1030,"y":2320},{"x":1030,"y":2340}],"counts":[1,1,1]},{"startIndex":61,"endIndex":63,"startConnectorIndex":1,"endConnectorIndex":3,"nodes":[{"x":1080,"y":2360},{"x":1100,"y":2360},{"x":1120,"y":2360}],"counts":[1,1,1]},{"startIndex":61,"endIndex":62,"startConnectorIndex":3,"endConnectorIndex":0,"nodes":[{"x":980,"y":2360},{"x":960,"y":2360},{"x":960,"y":2390},{"x":1030,"y":2390},{"x":1030,"y":2410}],"counts":[1,1,1,1,1]},{"startIndex":63,"endIndex":62,"startConnectorIndex":1,"endConnectorIndex":0,"nodes":[{"x":1220,"y":2360},{"x":1240,"y":2360},{"x":1240,"y":2390},{"x":1030,"y":2390},{"x":1030,"y":2410}],"counts":[1,1,1,1,1]},{"startIndex":62,"endIndex":64,"startConnectorIndex":1,"endConnectorIndex":3,"nodes":[{"x":1080,"y":2430},{"x":1100,"y":2430},{"x":1120,"y":2430}],"counts":[1,1,1]},{"startIndex":62,"endIndex":60,"startConnectorIndex":3,"endConnectorIndex":1,"nodes":[{"x":980,"y":2430},{"x":960,"y":2430},{"x":960,"y":2480},{"x":1270,"y":2480},{"x":1270,"y":2300},{"x":1120,"y":2300},{"x":1100,"y":2300}],"counts":[1,1,1,1,1,1,1]},{"startIndex":64,"endIndex":60,"startConnectorIndex":1,"endConnectorIndex":1,"nodes":[{"x":1220,"y":2430},{"x":1270,"y":2430},{"x":1270,"y":2300},{"x":1120,"y":2300},{"x":1100,"y":2300}],"counts":[1,1,1,1,1]},{"startIndex":66,"endIndex":69,"startConnectorIndex":2,"endConnectorIndex":0,"nodes":[{"x":1160,"y":2590},{"x":1160,"y":2590},{"x":1160,"y":2610}],"counts":[1,1,1]},{"startIndex":69,"endIndex":67,"startConnectorIndex":2,"endConnectorIndex":0,"nodes":[{"x":1160,"y":2650},{"x":1160,"y":2650},{"x":1160,"y":2670}],"counts":[1,1,1]},{"startIndex":65,"endIndex":66,"startConnectorIndex":1,"endConnectorIndex":0,"nodes":[{"x":1080,"y":2550},{"x":1100,"y":2550},{"x":1100,"y":2530},{"x":1160,"y":2530},{"x":1160,"y":2550}],"counts":[1,1,1,1,1]},{"startIndex":67,"endIndex":68,"startConnectorIndex":2,"endConnectorIndex":0,"nodes":[{"x":1160,"y":2710},{"x":1160,"y":2730},{"x":1030,"y":2730},{"x":1030,"y":2745}],"counts":[1,1,1,1]},{"startIndex":65,"endIndex":68,"startConnectorIndex":3,"endConnectorIndex":0,"nodes":[{"x":980,"y":2550},{"x":960,"y":2550},{"x":960,"y":2730},{"x":1030,"y":2730},{"x":1030,"y":2745}],"counts":[1,1,1,1,1]},{"startIndex":60,"endIndex":65,"startConnectorIndex":3,"endConnectorIndex":0,"nodes":[{"x":960,"y":2300},{"x":940,"y":2300},{"x":940,"y":2510},{"x":1030,"y":2510},{"x":1030,"y":2530}],"counts":[1,1,1,1,1]},{"startIndex":14,"endIndex":13,"startConnectorIndex":3,"endConnectorIndex":1,"nodes":[{"x":270,"y":1040},{"x":250,"y":1040},{"x":250,"y":1200},{"x":640,"y":1200},{"x":640,"y":980},{"x":450,"y":980}],"counts":[1,1,1,1,1,1]},{"startIndex":16,"endIndex":17,"startConnectorIndex":2,"endConnectorIndex":0,"nodes":[{"x":570,"y":1170},{"x":570,"y":1210},{"x":400,"y":1210},{"x":400,"y":1230}],"counts":[1,1,1,1]},{"startIndex":71,"endIndex":72,"startConnectorIndex":2,"endConnectorIndex":0,"nodes":[{"x":1460,"y":2145},{"x":1460,"y":2150},{"x":1460,"y":2170}],"counts":[1,1,1]},{"startIndex":72,"endIndex":73,"startConnectorIndex":2,"endConnectorIndex":0,"nodes":[{"x":1460,"y":2210},{"x":1460,"y":2210},{"x":1460,"y":2230}],"counts":[1,1,1]},{"startIndex":73,"endIndex":74,"startConnectorIndex":2,"endConnectorIndex":0,"nodes":[{"x":1460,"y":2270},{"x":1460,"y":2270},{"x":1460,"y":2290}],"counts":[1,1,1]},{"startIndex":76,"endIndex":77,"startConnectorIndex":2,"endConnectorIndex":0,"nodes":[{"x":1610,"y":2440},{"x":1610,"y":2440},{"x":1610,"y":2460}],"counts":[1,1,1]},{"startIndex":75,"endIndex":76,"startConnectorIndex":2,"endConnectorIndex":0,"nodes":[{"x":1610,"y":2380},{"x":1610,"y":2380},{"x":1610,"y":2400}],"counts":[1,1,1]},{"startIndex":77,"endIndex":78,"startConnectorIndex":2,"endConnectorIndex":0,"nodes":[{"x":1610,"y":2500},{"x":1610,"y":2500},{"x":1610,"y":2520}],"counts":[1,1,1]},{"startIndex":74,"endIndex":75,"startConnectorIndex":1,"endConnectorIndex":0,"nodes":[{"x":1570,"y":2310},{"x":1610,"y":2310},{"x":1610,"y":2320},{"x":1610,"y":2340}],"counts":[1,1,1,1]},{"startIndex":73,"endIndex":79,"startConnectorIndex":3,"endConnectorIndex":0,"nodes":[{"x":1410,"y":2250},{"x":1300,"y":2250},{"x":1300,"y":2640},{"x":1460,"y":2640},{"x":1460,"y":2655}],"counts":[1,1,1,1,1]},{"startIndex":74,"endIndex":73,"startConnectorIndex":3,"endConnectorIndex":1,"nodes":[{"x":1350,"y":2310},{"x":1330,"y":2310},{"x":1330,"y":2600},{"x":1700,"y":2600},{"x":1700,"y":2250},{"x":1510,"y":2250}],"counts":[1,1,1,1,1,1]},{"startIndex":78,"endIndex":79,"startConnectorIndex":2,"endConnectorIndex":0,"nodes":[{"x":1610,"y":2560},{"x":1610,"y":2640},{"x":1460,"y":2640},{"x":1460,"y":2655}],"counts":[1,1,1,1]},{"startIndex":81,"endIndex":82,"startConnectorIndex":2,"endConnectorIndex":0,"nodes":[{"x":1900,"y":2175},{"x":1900,"y":2180},{"x":1900,"y":2200}],"counts":[1,1,1]},{"startIndex":82,"endIndex":83,"startConnectorIndex":2,"endConnectorIndex":0,"nodes":[{"x":1900,"y":2240},{"x":1900,"y":2240},{"x":1900,"y":2260}],"counts":[1,1,1]},{"startIndex":83,"endIndex":82,"startConnectorIndex":1,"endConnectorIndex":1,"nodes":[{"x":1960,"y":2280},{"x":1990,"y":2280},{"x":1990,"y":2220},{"x":1970,"y":2220},{"x":1950,"y":2220}],"counts":[1,1,1,1,1]},{"startIndex":82,"endIndex":84,"startConnectorIndex":3,"endConnectorIndex":0,"nodes":[{"x":1850,"y":2220},{"x":1800,"y":2220},{"x":1800,"y":2320},{"x":1900,"y":2320},{"x":1900,"y":2340}],"counts":[1,1,1,1,1]},{"startIndex":84,"endIndex":85,"startConnectorIndex":2,"endConnectorIndex":0,"nodes":[{"x":1900,"y":2380},{"x":1900,"y":2380},{"x":1900,"y":2400}],"counts":[1,1,1]},{"startIndex":85,"endIndex":84,"startConnectorIndex":1,"endConnectorIndex":1,"nodes":[{"x":1980,"y":2420},{"x":2010,"y":2420},{"x":2010,"y":2360},{"x":1970,"y":2360},{"x":1950,"y":2360}],"counts":[1,1,1,1,1]},{"startIndex":84,"endIndex":86,"startConnectorIndex":3,"endConnectorIndex":0,"nodes":[{"x":1850,"y":2360},{"x":1800,"y":2360},{"x":1800,"y":2460},{"x":1900,"y":2460},{"x":1900,"y":2475}],"counts":[1,1,1,1,1]},{"startIndex":88,"endIndex":89,"startConnectorIndex":2,"endConnectorIndex":0,"nodes":[{"x":2140,"y":2165},{"x":2140,"y":2170},{"x":2140,"y":2190}],"counts":[1,1,1]},{"startIndex":90,"endIndex":91,"startConnectorIndex":2,"endConnectorIndex":0,"nodes":[{"x":2250,"y":2280},{"x":2250,"y":2280},{"x":2250,"y":2300}],"counts":[1,1,1]},{"startIndex":89,"endIndex":90,"startConnectorIndex":1,"endConnectorIndex":0,"nodes":[{"x":2190,"y":2210},{"x":2250,"y":2210},{"x":2250,"y":2220},{"x":2250,"y":2240}],"counts":[1,1,1,1]},{"startIndex":91,"endIndex":92,"startConnectorIndex":2,"endConnectorIndex":0,"nodes":[{"x":2250,"y":2340},{"x":2250,"y":2360},{"x":2140,"y":2360},{"x":2140,"y":2375}],"counts":[1,1,1,1]},{"startIndex":89,"endIndex":92,"startConnectorIndex":3,"endConnectorIndex":0,"nodes":[{"x":2090,"y":2210},{"x":2070,"y":2210},{"x":2070,"y":2360},{"x":2140,"y":2360},{"x":2140,"y":2375}],"counts":[1,1,1,1,1]},{"startIndex":94,"endIndex":95,"startConnectorIndex":2,"endConnectorIndex":0,"nodes":[{"x":2440,"y":2165},{"x":2440,"y":2170},{"x":2440,"y":2190}],"counts":[1,1,1]},{"startIndex":95,"endIndex":96,"startConnectorIndex":2,"endConnectorIndex":0,"nodes":[{"x":2440,"y":2230},{"x":2440,"y":2230},{"x":2440,"y":2250}],"counts":[1,1,1]},{"startIndex":96,"endIndex":97,"startConnectorIndex":2,"endConnectorIndex":0,"nodes":[{"x":2440,"y":2290},{"x":2440,"y":2290},{"x":2440,"y":2305}],"counts":[1,1,1]}],"x0":366.6875,"y0":61.104166666666686}